smartfeed/__init__.py
smartfeed/examples/__init__.py
smartfeed/examples/example_client.py
smartfeed/manager.py
smartfeed/schemas.py
epoch8_smartfeed-0.1.0.dist-info/LICENSE
epoch8_smartfeed-0.1.0.dist-info/METADATA
epoch8_smartfeed-0.1.0.dist-info/WHEEL
epoch8_smartfeed-0.1.0.dist-info/RECORD
