Metadata-Version: 2.1
Name: epoch8-smartfeed
Version: 0.1.0
Summary: 
Author: Sultan Zakariya
Author-email: sultik10@gmail.com
Requires-Python: >=3.9
Classifier: Programming Language :: Python :: 3
Classifier: Programming Language :: Python :: 3.9
Classifier: Programming Language :: Python :: 3.10
Classifier: Programming Language :: Python :: 3.11
Classifier: Programming Language :: Python :: 3.12
Classifier: Programming Language :: Python :: 3.13
Requires-Dist: pydantic (>=1.10.7,<2.0.0)
Requires-Dist: redis (>=4.5.5,<5.0.0)
